{
    "total_time": 1102.790667295456,
    "iterations": 1000,
    "device": "cuda",
    "style_name": "sunset",
    "noise_ratio": 0.7,
    "learning_rate": 0.4,
    "final_losses": {
        "content_loss": 9.386640548706055,
        "style_loss": 0.07594163715839386,
        "tv_loss": 0.33247309923171997,
        "total_loss": 13.349959373474121
    },
    "args": {
        "noise_ratio": 0.7,
        "content_image": "./imgs/golden_gate.jpg",
        "style_image": "./imgs/sunset.jpeg",
        "content_loss_weight": 1.0,
        "style_loss_weight": 50.0,
        "tv_loss_weight": 0.5,
        "iteration": 1000,
        "imsize": 256,
        "save_freq": 250,
        "learning_rate": 0.4,
        "save_path": "outputs"
    }
}